dart_fss_classifier/__init__.py
dart_fss_classifier/_version.py
dart_fss_classifier/classifier.py
dart_fss_classifier/fs_search.py
dart_fss_classifier/data/dict.json
dart_fss_classifier/data/model.h5
dart_fss_classifier-0.2.0.dist-info/LICENSE
dart_fss_classifier-0.2.0.dist-info/METADATA
dart_fss_classifier-0.2.0.dist-info/WHEEL
dart_fss_classifier-0.2.0.dist-info/top_level.txt
dart_fss_classifier-0.2.0.dist-info/RECORD
