Metadata-Version: 2.1
Name: dart-fss-classifier
Version: 0.2.0
Summary: Plugin for dart-fss
Home-page: https://github.com/josw123/dart-fss-classifier
Author: Sungwoo Jo
Author-email: nonswing.z@gmail.com
License: GPLv3+
Keywords: fss,dart-fss,scrapping,plugin
Platform: UNKNOWN
Classifier: License :: OSI Approved :: GNU General Public License v3 or later (GPLv3+)
Classifier: Programming Language :: Python :: 3.5
Classifier: Programming Language :: Python :: 3.6
Classifier: Programming Language :: Python :: 3.7
Classifier: Programming Language :: Python :: 3 :: Only
Requires-Python: >=3.5
Requires-Dist: dart-fss (>=0.2.0)
Requires-Dist: tensorflow
Requires-Dist: konlpy
